eds/__init__.py
eds/Kollmorgen_AKD NBEI.eds
eds/Kollmorgen_AKD2G-SPI.eds
eds/METTLER TOLEDO_ACT350.eds
eds/Moxa_E1212.eds
eds/Moxa_E1242.eds
eds/Nanotec_C5-E-1-11.eds
eds/Nanotec_C5-E-2-11.eds
eds/parser.py
eip/__init__.py
eip/__main__.py
eip/cip.py
eip/client.py
eip/controller_libraries/nanotec_motor_controller/NanotecC5E11ExplicitController.py
eip/controller_libraries/nanotec_motor_controller/NanotecCE5MotorController.py
eip/controller_libraries/tests/tcp_test_motor_controller.py
eip/controller_libraries/tests/udp_test_motor_controller.py
eip/controller_libraries/tests/VannexTester.py
eip/encapsulation.py
eip/models.py
procaaso_eip-0.1.7.dist-info/entry_points.txt
procaaso_eip-0.1.7.dist-info/LICENSE
procaaso_eip-0.1.7.dist-info/METADATA
procaaso_eip-0.1.7.dist-info/WHEEL
procaaso_eip-0.1.7.dist-info/RECORD
