Metadata-Version: 2.1
Name: procaaso-eip
Version: 0.1.7
Summary: 
Author: Brandon Smith
Author-email: bsmith@consynsys.com
Requires-Python: >=3.10,<4.0
Classifier: Programming Language :: Python :: 3
Classifier: Programming Language :: Python :: 3.10
Classifier: Programming Language :: Python :: 3.11
Classifier: Programming Language :: Python :: 3.12
Requires-Dist: click (>=8.1.7,<9.0.0)
Requires-Dist: cpppo (>=4.4.2,<5.0.0)
Requires-Dist: pydantic (>=1.10.9,<2.0.0)
Requires-Dist: pyyaml (>=6.0.1,<7.0.0)
Requires-Dist: requests (>=2.28.1,<3.0.0)
Requires-Dist: scapy (>=2.6.0,<3.0.0)
